sls_tools/__init__.py
sls_tools/param_store/__init__.py
sls_tools/param_store/param_store.py
sls_tools/param_store/param_store_result.py
sls_tools-0.0.4.dist-info/LICENSE
sls_tools-0.0.4.dist-info/METADATA
sls_tools-0.0.4.dist-info/NOTICE
sls_tools-0.0.4.dist-info/WHEEL
sls_tools-0.0.4.dist-info/top_level.txt
sls_tools-0.0.4.dist-info/RECORD
