Metadata-Version: 2.1
Name: sls-tools
Version: 0.0.4
Summary: Utilities for developing AWS Lambda functions in Python.
Home-page: https://github.com/ki-tools/sls-tools-py
Author: Patrick Stout
Author-email: pstout@prevagroup.com
License: Apache2
Platform: UNKNOWN
Classifier: Programming Language :: Python
Classifier: Programming Language :: Python :: 3.6
Classifier: Programming Language :: Python :: 3.7
Classifier: Programming Language :: Python :: 3.8
Classifier: Programming Language :: Python :: 3.9
Classifier: Programming Language :: Python :: 3.10
Classifier: License :: OSI Approved :: Apache Software License
Classifier: Operating System :: OS Independent
License-File: LICENSE
License-File: NOTICE
Requires-Dist: boto3
